ux_watcher/__init__.py
ux_watcher/__main__.py
ux_watcher/browser.py
ux_watcher/gemini.py
ux_watcher/server.py
ux_lens-0.1.1.dist-info/METADATA
ux_lens-0.1.1.dist-info/WHEEL
ux_lens-0.1.1.dist-info/entry_points.txt
ux_lens-0.1.1.dist-info/RECORD
