Metadata-Version: 2.4
Name: ux-lens
Version: 0.1.1
Summary: MCP server for browser-based UX critique with Gemini
Requires-Python: >=3.11
Requires-Dist: google-genai>=1.0.0
Requires-Dist: mcp>=1.25.0
Requires-Dist: playwright>=1.57.0
